README.md
setup.cfg
setup.py
Topsis_Utkarsh_101903139.egg-info/PKG-INFO
Topsis_Utkarsh_101903139.egg-info/SOURCES.txt
Topsis_Utkarsh_101903139.egg-info/dependency_links.txt
Topsis_Utkarsh_101903139.egg-info/entry_points.txt
Topsis_Utkarsh_101903139.egg-info/requires.txt
Topsis_Utkarsh_101903139.egg-info/top_level.txt
topsis/__init__.py
topsis/topsis.py