Metadata-Version: 1.1
Name: Topsis-Utkarsh-101903139
Version: 1.0.6
Summary: A Python package implementing TOPSIS technique.
Home-page: UNKNOWN
Author: Utkarsh Sangwan
Author-email: utkarshsangwan7@gmail.com
License: MIT
Platform: UNKNOWN
Classifier: License :: OSI Approved :: MIT License
Classifier: Programming Language :: Python :: 3
Classifier: Programming Language :: Python :: 3.7
